{"version":1,"resource":"file:///home/jagannathanm/private-repo2/docker-compose.yml","entries":[{"id":"Kyfg.yml","timestamp":1690537041190},{"id":"Ljbd.yml","timestamp":1690541848277},{"id":"yAjB.yml","timestamp":1690541914480},{"id":"LGWO.yml","timestamp":1690542030132},{"id":"hjfm.yml","timestamp":1690545325599},{"id":"xZnR.yml","timestamp":1690545913082},{"id":"JUZ5.yml","timestamp":1690546055530},{"id":"hUc6.yml","timestamp":1690546559623},{"id":"cGa3.yml","timestamp":1690558587216},{"id":"l8N5.yml","timestamp":1690568803458},{"id":"ifv7.yml","timestamp":1690569644431},{"id":"OCbP.yml","timestamp":1690571230891},{"id":"ZnBn.yml","timestamp":1690571550661},{"id":"r83x.yml","timestamp":1690579732794},{"id":"gJxg.yml","timestamp":1690656184051},{"id":"2OxB.yml","timestamp":1690656209055},{"id":"9cux.yml","timestamp":1690664172241},{"id":"6NPU.yml","timestamp":1690702832881},{"id":"xYy4.yml","source":"undoRedo.source","timestamp":1690702970907},{"id":"d5b1.yml","timestamp":1690703138049},{"id":"iY5f.yml","timestamp":1690703583275},{"id":"6hp8.yml","timestamp":1690703618586},{"id":"5rCC.yml","timestamp":1690705721892},{"id":"jQjU.yml","source":"undoRedo.source","timestamp":1690705929524},{"id":"P0j5.yml","timestamp":1690706127294},{"id":"Kocm.yml","timestamp":1690706138651},{"id":"CEXy.yml","timestamp":1690708632977},{"id":"N4u1.yml","timestamp":1690712112663},{"id":"PMw9.yml","timestamp":1690715173929}]}