{"version":1,"resource":"file:///home/jagannathanm/programs/Rust/rustlings/exercises/lifetimes/lifetimes2.rs","entries":[{"id":"Lmj4.rs","timestamp":1696078070197},{"id":"s60f.rs","timestamp":1696078082280},{"id":"QSco.rs","timestamp":1696078094584},{"id":"Wdzb.rs","timestamp":1696078110761},{"id":"lh1V.rs","timestamp":1696078166014},{"id":"3Jof.rs","timestamp":1696078239742},{"id":"rduh.rs","source":"undoRedo.source","timestamp":1696078377133},{"id":"EEya.rs","timestamp":1696078978871},{"id":"8woy.rs","timestamp":1696079004638},{"id":"Sx8V.rs","timestamp":1696079281004},{"id":"TQXC.rs","timestamp":1696079300514}]}